<?xml version="1.0" encoding="UTF-8"?>
<beans xmlns="http://www.springframework.org/schema/beans"
	xmlns:xsi="http://www.w3.org/2001/XMLSchema-instance"
	xmlns:context="http://www.springframework.org/schema/context"
	xsi:schemaLocation="http://www.springframework.org/schema/beans http://www.springframework.org/schema/beans/spring-beans.xsd
		http://www.springframework.org/schema/context http://www.springframework.org/schema/context/spring-context-4.2.xsd">
    
<!-- ShareListService -->
<bean id="shareListService" class="com.traveler.service.ShareListService">
	<property name="shareDao" ref="shareDao"></property>
</bean>    

<!-- SharePageService -->
<bean id="sharePageService" class="com.traveler.service.SharePageService">
	<property name="shareDao" ref="shareDao"></property>
</bean>

<!-- ShareDetailService -->
<bean id="shareDetailService" class="com.traveler.service.ShareDetailService">
    <property name="shareDao" ref="shareDao"/>
</bean>

<!-- ShareRegisterService -->
<bean id="shareRegisterService" class="com.traveler.service.ShareRegisterService">
	<property name="shareDao" ref="shareDao"></property>
</bean>

<!-- ShareUnRegisterService -->
<bean id="shareUnRegisterService" class="com.traveler.service.ShareUnRegisterService">
	<property name="shareDao" ref="shareDao"></property>
</bean>

<!-- ShareModifyService -->
<bean id="shareModifyService" class="com.traveler.service.ShareModifyService">
	<property name="shareDao" ref="shareDao"></property>
</bean>
    
    
<bean id="recommandListService" class="com.traveler.service.RecommandListService">
    <property name="recommandDao" ref="recommandDao"/>
</bean>
  
<bean id="recommandPageService" class="com.traveler.service.RecommandPageService">
    <property name="recommandDao" ref="recommandDao"/>
</bean>

<bean id="recommandRegisterService" class="com.traveler.service.RecommandRegisterService">
    <property name="recommandDao" ref="recommandDao"/>
</bean>
    
    <!-- MemberListService -->
<bean id="memberListService" class="com.traveler.service.MemberListService">
	    <property name="memberDao" ref="memberDao"/>
</bean>
    
</beans>
